README.md
setup.py
geocloud_es/__init__.py
geocloud_es.egg-info/PKG-INFO
geocloud_es.egg-info/SOURCES.txt
geocloud_es.egg-info/dependency_links.txt
geocloud_es.egg-info/entry_points.txt
geocloud_es.egg-info/requires.txt
geocloud_es.egg-info/top_level.txt