Metadata-Version: 2.1
Name: geocloud-es
Version: 0.8
Summary: ElasticSearch ingestor for GPSD JSON
Home-page: https://github.com/innovationgarage/geocloud-es
Author: Egil Moeller
Author-email: egil@innovationgarage.no
License: UNKNOWN
Platform: UNKNOWN
